{"cameraMode":{"drawMode":0,"name":"Shaded","section":"Shading Mode"},"sceneLighting":false,"audioPlay":false,"sceneViewState":{"m_AlwaysRefresh":false,"showFog":true,"showSkybox":false,"showFlares":true,"showImageEffects":true,"showParticleSystems":true,"showVisualEffectGraphs":true,"m_FxEnabled":true},"in2DMode":false,"pivot":{"x":-17.247007369995118,"y":25.38945960998535,"z":-246.2745361328125},"rotation":{"x":0.06741706281900406,"y":-0.1868477314710617,"z":-0.012873238883912564,"w":-0.9799944162368774},"size":37.381187438964847,"orthographic":false}